{"format":1,"version":"4.5.3","settings":"b3a0bff7154d5bbec34fcac359c54f68","files":{"PostIt___init___py":{"hash":"182b2dca469bf063cbcf996d517b03da","index":{"nums":[1,0,0,0,0,0,0],"html_filename":"PostIt___init___py.html","relative_filename":"PostIt\\__init__.py"}},"PostIt_settings_py":{"hash":"e4d32912420f11b5d20abbe4bfb790c0","index":{"nums":[1,30,0,0,0,0,0],"html_filename":"PostIt_settings_py.html","relative_filename":"PostIt\\settings.py"}},"PostIt_urls_py":{"hash":"c1a53e130fab44441c2112e2a5223c5d","index":{"nums":[1,7,0,0,0,0,0],"html_filename":"PostIt_urls_py.html","relative_filename":"PostIt\\urls.py"}},"PostIt_wsgi_py":{"hash":"b39c1eadf7e3a013809335f66b912505","index":{"nums":[1,4,0,4,0,0,0],"html_filename":"PostIt_wsgi_py.html","relative_filename":"PostIt\\wsgi.py"}},"accounts___init___py":{"hash":"182b2dca469bf063cbcf996d517b03da","index":{"nums":[1,0,0,0,0,0,0],"html_filename":"accounts___init___py.html","relative_filename":"accounts\\__init__.py"}},"accounts_admin_py":{"hash":"3e2e151ab880b96e471617e98dce675b","index":{"nums":[1,3,0,0,0,0,0],"html_filename":"accounts_admin_py.html","relative_filename":"accounts\\admin.py"}},"accounts_apps_py":{"hash":"024a03e6cf0467fcab993bf5dddd56ce","index":{"nums":[1,3,0,3,0,0,0],"html_filename":"accounts_apps_py.html","relative_filename":"accounts\\apps.py"}},"accounts_forms_py":{"hash":"d063ff38195c5c5247cb161b3945613e","index":{"nums":[1,27,0,7,0,0,0],"html_filename":"accounts_forms_py.html","relative_filename":"accounts\\forms.py"}},"accounts_migrations_0001_initial_py":{"hash":"189603f501db76d9a53a368cb962f151","index":{"nums":[1,7,0,0,0,0,0],"html_filename":"accounts_migrations_0001_initial_py.html","relative_filename":"accounts\\migrations\\0001_initial.py"}},"accounts_migrations___init___py":{"hash":"182b2dca469bf063cbcf996d517b03da","index":{"nums":[1,0,0,0,0,0,0],"html_filename":"accounts_migrations___init___py.html","relative_filename":"accounts\\migrations\\__init__.py"}},"accounts_models_py":{"hash":"b6aa2ff1c767b7c16c2a05cdf75abfbd","index":{"nums":[1,12,0,1,0,0,0],"html_filename":"accounts_models_py.html","relative_filename":"accounts\\models.py"}},"accounts_tests_py":{"hash":"103a941ba351047966237b335cdbeab5","index":{"nums":[1,17,0,0,0,0,0],"html_filename":"accounts_tests_py.html","relative_filename":"accounts\\tests.py"}},"accounts_urls_py":{"hash":"7378da103611d5b4b0bedd14ee7824b7","index":{"nums":[1,4,0,0,0,0,0],"html_filename":"accounts_urls_py.html","relative_filename":"accounts\\urls.py"}},"accounts_views_py":{"hash":"bf6a30485f11c96c0e2aaaf5dc6e9674","index":{"nums":[1,27,0,6,0,0,0],"html_filename":"accounts_views_py.html","relative_filename":"accounts\\views.py"}},"manage_py":{"hash":"bbdf7dc41f1a2dadf97cd8b29d7d24cf","index":{"nums":[1,12,0,2,0,0,0],"html_filename":"manage_py.html","relative_filename":"manage.py"}},"postitapp___init___py":{"hash":"182b2dca469bf063cbcf996d517b03da","index":{"nums":[1,0,0,0,0,0,0],"html_filename":"postitapp___init___py.html","relative_filename":"postitapp\\__init__.py"}},"postitapp_admin_py":{"hash":"60bd935e788914606f7a06ac1dffe1a4","index":{"nums":[1,5,0,0,0,0,0],"html_filename":"postitapp_admin_py.html","relative_filename":"postitapp\\admin.py"}},"postitapp_apps_py":{"hash":"75b0d749882e5fc1c7ae828680c638ed","index":{"nums":[1,3,0,3,0,0,0],"html_filename":"postitapp_apps_py.html","relative_filename":"postitapp\\apps.py"}},"postitapp_migrations_0001_initial_py":{"hash":"d3f229e3ae0efc486e2e3a5e2dbbb8eb","index":{"nums":[1,7,0,0,0,0,0],"html_filename":"postitapp_migrations_0001_initial_py.html","relative_filename":"postitapp\\migrations\\0001_initial.py"}},"postitapp_migrations_0002_auto_20190530_1506_py":{"hash":"914cb5aca540b3f9ebafd6dced351d1d","index":{"nums":[1,6,0,0,0,0,0],"html_filename":"postitapp_migrations_0002_auto_20190530_1506_py.html","relative_filename":"postitapp\\migrations\\0002_auto_20190530_1506.py"}},"postitapp_migrations___init___py":{"hash":"182b2dca469bf063cbcf996d517b03da","index":{"nums":[1,0,0,0,0,0,0],"html_filename":"postitapp_migrations___init___py.html","relative_filename":"postitapp\\migrations\\__init__.py"}},"postitapp_models_py":{"hash":"2ca2de9f65b9c1bcac6d1c8d833f07a9","index":{"nums":[1,16,0,0,0,0,0],"html_filename":"postitapp_models_py.html","relative_filename":"postitapp\\models.py"}},"postitapp_tests_py":{"hash":"04092228bac7be9b4120abcfc9efd3d8","index":{"nums":[1,128,0,0,0,0,0],"html_filename":"postitapp_tests_py.html","relative_filename":"postitapp\\tests.py"}},"postitapp_urls_py":{"hash":"3bf6d300f3d830060e080a4908528521","index":{"nums":[1,5,0,0,0,0,0],"html_filename":"postitapp_urls_py.html","relative_filename":"postitapp\\urls.py"}},"postitapp_views_py":{"hash":"19a9feeda1353b3bb7e02b4e755c23ac","index":{"nums":[1,105,0,0,0,0,0],"html_filename":"postitapp_views_py.html","relative_filename":"postitapp\\views.py"}},"postitlogin___init___py":{"hash":"182b2dca469bf063cbcf996d517b03da","index":{"nums":[1,0,0,0,0,0,0],"html_filename":"postitlogin___init___py.html","relative_filename":"postitlogin\\__init__.py"}},"postitlogin_admin_py":{"hash":"bc129b691954ee2acd33c858dc27ce73","index":{"nums":[1,1,0,0,0,0,0],"html_filename":"postitlogin_admin_py.html","relative_filename":"postitlogin\\admin.py"}},"postitlogin_apps_py":{"hash":"e5857f43503fe886e68ffdd50b24554f","index":{"nums":[1,3,0,3,0,0,0],"html_filename":"postitlogin_apps_py.html","relative_filename":"postitlogin\\apps.py"}},"postitlogin_migrations___init___py":{"hash":"182b2dca469bf063cbcf996d517b03da","index":{"nums":[1,0,0,0,0,0,0],"html_filename":"postitlogin_migrations___init___py.html","relative_filename":"postitlogin\\migrations\\__init__.py"}},"postitlogin_models_py":{"hash":"2a9c97b9f7e011df98f188fdacee0b6c","index":{"nums":[1,1,0,0,0,0,0],"html_filename":"postitlogin_models_py.html","relative_filename":"postitlogin\\models.py"}},"postitlogin_tests_py":{"hash":"d6c27ce6bbdf993ddddd74ab139e9958","index":{"nums":[1,1,0,0,0,0,0],"html_filename":"postitlogin_tests_py.html","relative_filename":"postitlogin\\tests.py"}},"postitlogin_urls_py":{"hash":"e72e61831cbe757766cdf8ed84a12fe2","index":{"nums":[1,5,0,0,0,0,0],"html_filename":"postitlogin_urls_py.html","relative_filename":"postitlogin\\urls.py"}},"postitlogin_views_py":{"hash":"64888908ad2023b55f343855287475ef","index":{"nums":[1,1,0,0,0,0,0],"html_filename":"postitlogin_views_py.html","relative_filename":"postitlogin\\views.py"}}}}